PhenotypeSeeker/__init__.py
PhenotypeSeeker/modeling.py
PhenotypeSeeker/prediction.py
PhenotypeSeeker-0.0.0.data/scripts/phenotypeseeker
PhenotypeSeeker-0.0.0.dist-info/DESCRIPTION.rst
PhenotypeSeeker-0.0.0.dist-info/METADATA
PhenotypeSeeker-0.0.0.dist-info/RECORD
PhenotypeSeeker-0.0.0.dist-info/WHEEL
PhenotypeSeeker-0.0.0.dist-info/metadata.json
PhenotypeSeeker-0.0.0.dist-info/top_level.txt
