Metadata-Version: 2.0
Name: PhenotypeSeeker
Version: 0.0.0
Summary: Identifies phenotype-specific k-mers, creates phenotype           prediction models and using this model predicts phenotype from           sequenced bacterial strains
Home-page: https://www.bioinfo.ut.ee/PhenotypeSeeker
Author: Erki Aun
Author-email: erki.aun@ut.ee
License: UNKNOWN
Platform: UNKNOWN
Requires-Dist: Biopython
Requires-Dist: cogent
Requires-Dist: numpy
Requires-Dist: scipy
Requires-Dist: scikit-learn
